expressipy/__init__.py
expressipy/client.py
expressipy/enums.py
expressipy/exceptions.py
expressipy/http.py
expressipy/models.py
expressipy/py.typed
expressipy/types.py
expressipy/utils/__init__.py
expressipy/utils/formatter.py
expressipy-2.1.0.dist-info/licenses/LICENSE
expressipy-2.1.0.dist-info/METADATA
expressipy-2.1.0.dist-info/WHEEL
expressipy-2.1.0.dist-info/top_level.txt
expressipy-2.1.0.dist-info/RECORD
